mlopspython_extraction/__init__.py
mlopspython_extraction/extraction.py
mlopspython_extraction-8761634318759538533639.dist-info/METADATA
mlopspython_extraction-8761634318759538533639.dist-info/WHEEL
mlopspython_extraction-8761634318759538533639.dist-info/top_level.txt
mlopspython_extraction-8761634318759538533639.dist-info/RECORD
